{
    "Ar36": {
        "error": 0.0005462643968180481, 
        "filter_outliers_dict": {
            "filter_outliers": true, 
            "iterations": 2, 
            "std_devs": 2
        }, 
        "fit": "Parabolic", 
        "value": 0.045250622344271255
    }, 
    "Ar37": {
        "error": 0.011740527661386321, 
        "filter_outliers_dict": {
            "filter_outliers": true, 
            "iterations": 2, 
            "std_devs": 2
        }, 
        "fit": "linear", 
        "value": -0.25998704074803813
    }, 
    "Ar38": {
        "error": 0.013380417941755835, 
        "filter_outliers_dict": {
            "filter_outliers": true, 
            "iterations": 2, 
            "std_devs": 2
        }, 
        "fit": "linear", 
        "value": 1.4485502886404271
    }, 
    "Ar39": {
        "error": 0.030594311432019204, 
        "filter_outliers_dict": {
            "filter_outliers": true, 
            "iterations": 2, 
            "std_devs": 2
        }, 
        "fit": "Parabolic", 
        "value": 122.0604989544317
    }, 
    "Ar40": {
        "error": 0.07782896705768352, 
        "filter_outliers_dict": {
            "filter_outliers": true, 
            "iterations": 2, 
            "std_devs": 2
        }, 
        "fit": "Parabolic", 
        "value": 1509.286980914224
    }
}