{
    "Ar36": {
        "error": 0.0005245625788817664, 
        "filter_outliers_dict": {
            "filter_outliers": true, 
            "iterations": 2, 
            "std_devs": 2
        }, 
        "fit": "Parabolic", 
        "value": 0.04546746181774121
    }, 
    "Ar37": {
        "error": 0.011922351914247181, 
        "filter_outliers_dict": {
            "filter_outliers": true, 
            "iterations": 2, 
            "std_devs": 2
        }, 
        "fit": "linear", 
        "value": -0.34955738670549413
    }, 
    "Ar38": {
        "error": 0.01297782582700862, 
        "filter_outliers_dict": {
            "filter_outliers": true, 
            "iterations": 2, 
            "std_devs": 2
        }, 
        "fit": "linear", 
        "value": 1.4197011108467477
    }, 
    "Ar39": {
        "error": 0.03450783659418133, 
        "filter_outliers_dict": {
            "filter_outliers": true, 
            "iterations": 2, 
            "std_devs": 2
        }, 
        "fit": "Parabolic", 
        "value": 119.32342687076235
    }, 
    "Ar40": {
        "error": 0.080577869286304, 
        "filter_outliers_dict": {
            "filter_outliers": true, 
            "iterations": 2, 
            "std_devs": 2
        }, 
        "fit": "Parabolic", 
        "value": 1477.410244095779
    }
}